[
  {
    "timestamp": "Tuesday, February 25, 2025 at 09:06:09 GMT+7",
    "message": "Server is running on port 3001"
  },
  {
    "timestamp": "Tuesday, February 25, 2025 at 09:08:05 GMT+7",
    "message": "Server is running on port 3001"
  },
  {
    "timestamp": "Tuesday, February 25, 2025 at 09:08:55 GMT+7",
    "message": "Report berhasil dikirim ke Sani dengan ID pesan: [don't replay] tester"
  },
  {
    "timestamp": "Tuesday, February 25, 2025 at 09:08:55 GMT+7",
    "message": "Report berhasil dikirim ke Katya Blinda Putri dengan ID pesan: [don't replay] tester"
  },
  {
    "timestamp": "Tuesday, February 25, 2025 at 09:12:53 GMT+7",
    "message": "Server is running on port 3001"
  },
  {
    "timestamp": "Tuesday, February 25, 2025 at 09:22:35 GMT+7",
    "message": "Server is running on port 3001"
  },
  {
    "timestamp": "Tuesday, February 25, 2025 at 09:25:19 GMT+7",
    "message": "Server is running on port 3001"
  },
  {
    "timestamp": "Tuesday, February 25, 2025 at 09:28:03 GMT+7",
    "message": "Server is running on port 3001"
  },
  {
    "timestamp": "Tuesday, February 25, 2025 at 09:32:25 GMT+7",
    "message": "Server is running on port 3001"
  },
  {
    "timestamp": "Tuesday, February 25, 2025 at 09:35:32 GMT+7",
    "message": "Server is running on port 3001"
  },
  {
    "timestamp": "Tuesday, February 25, 2025 at 09:35:59 GMT+7",
    "message": "File image type not supported"
  },
  {
    "timestamp": "Tuesday, February 25, 2025 at 09:35:59 GMT+7",
    "message": "File image type not supported"
  },
  {
    "timestamp": "Tuesday, February 25, 2025 at 09:42:24 GMT+7",
    "message": "Server is running on port 3001"
  },
  {
    "timestamp": "Tuesday, February 25, 2025 at 09:42:54 GMT+7",
    "message": "Report berhasil dikirim ke Sani dengan ID pesan: [don't replay] tester"
  },
  {
    "timestamp": "Tuesday, February 25, 2025 at 09:45:26 GMT+7",
    "message": "Server is running on port 3001"
  },
  {
    "timestamp": "Tuesday, February 25, 2025 at 09:45:58 GMT+7",
    "message": "Report berhasil dikirim ke Sani dengan ID pesan: [don't replay] tester"
  },
  {
    "timestamp": "Tuesday, February 25, 2025 at 09:45:58 GMT+7",
    "message": "Report berhasil dikirim ke Katya Blinda Putri dengan ID pesan: [don't replay] tester"
  },
  {
    "timestamp": "Tuesday, February 25, 2025 at 09:46:38 GMT+7",
    "message": "File image type not supported"
  },
  {
    "timestamp": "Tuesday, February 25, 2025 at 09:57:07 GMT+7",
    "message": "Server is running on port 3001"
  },
  {
    "timestamp": "Tuesday, February 25, 2025 at 09:58:14 GMT+7",
    "message": "File image type not supported, to user +62 822-8520-2656 please send image with type .jpg, .jpeg, .png"
  },
  {
    "timestamp": "Tuesday, February 25, 2025 at 09:58:14 GMT+7",
    "message": "Error sending message: ReferenceError: MessageMedia is not defined"
  },
  {
    "timestamp": "Tuesday, February 25, 2025 at 09:58:14 GMT+7",
    "message": "File image type not supported, to user +62 823-8595-0512 please send image with type .jpg, .jpeg, .png"
  },
  {
    "timestamp": "Tuesday, February 25, 2025 at 09:58:14 GMT+7",
    "message": "Error sending message: ReferenceError: MessageMedia is not defined"
  },
  {
    "timestamp": "Tuesday, February 25, 2025 at 10:09:53 GMT+7",
    "message": "Server is running on port 3001"
  },
  {
    "timestamp": "Tuesday, February 25, 2025 at 10:10:44 GMT+7",
    "message": "Server is running on port 3001"
  },
  {
    "timestamp": "Tuesday, February 25, 2025 at 10:11:08 GMT+7",
    "message": "Server is running on port 3001"
  },
  {
    "timestamp": "Tuesday, February 25, 2025 at 10:11:19 GMT+7",
    "message": "Server is running on port 3001"
  },
  {
    "timestamp": "Tuesday, February 25, 2025 at 10:14:44 GMT+7",
    "message": "Server is running on port 3001"
  },
  {
    "timestamp": "Tuesday, February 25, 2025 at 10:15:44 GMT+7",
    "message": "Server is running on port 3001"
  },
  {
    "timestamp": "Tuesday, February 25, 2025 at 10:15:59 GMT+7",
    "message": "Server is running on port 3001"
  },
  {
    "timestamp": "Tuesday, February 25, 2025 at 10:17:47 GMT+7",
    "message": "Server is running on port 3001"
  },
  {
    "timestamp": "Tuesday, February 25, 2025 at 10:24:49 GMT+7",
    "message": "Server is running on port 3001"
  },
  {
    "timestamp": "Tuesday, February 25, 2025 at 10:27:56 GMT+7",
    "message": "Server is running on port 3001"
  },
  {
    "timestamp": "Tuesday, February 25, 2025 at 10:35:56 GMT+7",
    "message": "Server is running on port 3001"
  },
  {
    "timestamp": "Tuesday, February 25, 2025 at 10:36:39 GMT+7",
    "message": "Server is running on port 3001"
  },
  {
    "timestamp": "Tuesday, February 25, 2025 at 10:37:51 GMT+7",
    "message": "Server is running on port 3001"
  },
  {
    "timestamp": "Tuesday, February 25, 2025 at 10:45:21 GMT+7",
    "message": "Server is running on port 3001"
  },
  {
    "timestamp": "Tuesday, February 25, 2025 at 10:46:11 GMT+7",
    "message": "Account 082285202656 destroyed successfully"
  },
  {
    "timestamp": "Tuesday, February 25, 2025 at 14:38:47 GMT+7",
    "message": "Server is running on port 3001"
  },
  {
    "timestamp": "Tuesday, February 25, 2025 at 14:39:26 GMT+7",
    "message": "Account 082285202656 destroyed successfully"
  },
  {
    "timestamp": "Tuesday, February 25, 2025 at 14:41:00 GMT+7",
    "message": "Server is running on port 3001"
  },
  {
    "timestamp": "Tuesday, February 25, 2025 at 14:41:10 GMT+7",
    "message": "\n        \n        ccount 082285202656 destroyed successfully"
  },
  {
    "timestamp": "Tuesday, February 25, 2025 at 14:42:10 GMT+7",
    "message": "Server is running on port 3001"
  },
  {
    "timestamp": "Tuesday, February 25, 2025 at 14:44:07 GMT+7",
    "message": "Server is running on port 3001"
  },
  {
    "timestamp": "Tuesday, February 25, 2025 at 14:44:26 GMT+7",
    "message": "Error destroyed account: Error: ENOENT: no such file or directory, lstat 'D:\\Web\\NodeJS\\whatsapp-web-api\\hooks\\sessions_auth\\session-082285202656'"
  },
  {
    "timestamp": "Tuesday, February 25, 2025 at 14:46:56 GMT+7",
    "message": "Server is running on port 3001"
  },
  {
    "timestamp": "Tuesday, February 25, 2025 at 14:47:19 GMT+7",
    "message": "\n        \n        ccount 082285202656 destroyed successfully"
  },
  {
    "timestamp": "Tuesday, February 25, 2025 at 14:49:55 GMT+7",
    "message": "Server is running on port 3001"
  },
  {
    "timestamp": "Tuesday, February 25, 2025 at 14:51:18 GMT+7",
    "message": "Server is running on port 3001"
  },
  {
    "timestamp": "Tuesday, February 25, 2025 at 14:51:44 GMT+7",
    "message": "Server is running on port 3001"
  },
  {
    "timestamp": "Tuesday, February 25, 2025 at 14:52:01 GMT+7",
    "message": "Server is running on port 3001"
  },
  {
    "timestamp": "Tuesday, February 25, 2025 at 14:53:55 GMT+7",
    "message": "Server is running on port 3001"
  },
  {
    "timestamp": "Tuesday, February 25, 2025 at 14:55:05 GMT+7",
    "message": "Server is running on port 3001"
  },
  {
    "timestamp": "Tuesday, February 25, 2025 at 14:57:16 GMT+7",
    "message": "Server is running on port 3001"
  },
  {
    "timestamp": "Tuesday, February 25, 2025 at 14:57:45 GMT+7",
    "message": "Server is running on port 3001"
  },
  {
    "timestamp": "Tuesday, February 25, 2025 at 14:58:50 GMT+7",
    "message": "\n        \n        ccount 082285202656 destroyed successfully"
  },
  {
    "timestamp": "Tuesday, February 25, 2025 at 15:00:43 GMT+7",
    "message": "Server is running on port 3001"
  },
  {
    "timestamp": "Tuesday, February 25, 2025 at 15:01:18 GMT+7",
    "message": "Server is running on port 3001"
  },
  {
    "timestamp": "Tuesday, February 25, 2025 at 15:03:13 GMT+7",
    "message": "Server is running on port 3001"
  },
  {
    "timestamp": "Tuesday, February 25, 2025 at 15:03:17 GMT+7",
    "message": "Account 082285202656 destroyed successfully"
  },
  {
    "timestamp": "Tuesday, February 25, 2025 at 15:03:57 GMT+7",
    "message": "Server is running on port 3001"
  },
  {
    "timestamp": "Tuesday, February 25, 2025 at 15:04:34 GMT+7",
    "message": "Server is running on port 3001"
  },
  {
    "timestamp": "Tuesday, February 25, 2025 at 15:05:03 GMT+7",
    "message": "Account 082285202656 destroyed successfully"
  },
  {
    "timestamp": "Tuesday, February 25, 2025 at 15:08:43 GMT+7",
    "message": "Server is running on port 3001"
  },
  {
    "timestamp": "Tuesday, February 25, 2025 at 15:09:56 GMT+7",
    "message": "Server is running on port 3001"
  },
  {
    "timestamp": "Tuesday, February 25, 2025 at 15:10:38 GMT+7",
    "message": "Server is running on port 3001"
  }
]